README.rst
setup.py
pyfoobot/__init__.py
pyfoobot.egg-info/PKG-INFO
pyfoobot.egg-info/SOURCES.txt
pyfoobot.egg-info/dependency_links.txt
pyfoobot.egg-info/requires.txt
pyfoobot.egg-info/top_level.txt