Metadata-Version: 1.1
Name: pyfoobot
Version: 0.2
Summary: A Python wrapper around the Foobot air quality API.
Home-page: https://github.com/philipbl/pyfoobot
Author: Philip Lundrigan
Author-email: philiplundrigan@gmail.com
License: MIT License
Download-URL: https://github.com/philipbl/pyfoobot/archive/0.2.zip
Keywords: air quality,sensor,IoT
Platform: any
Classifier: Intended Audience :: End Users/Desktop
Classifier: Intended Audience :: Developers
Classifier: License :: OSI Approved :: MIT License
Classifier: Operating System :: OS Independent
Classifier: Programming Language :: Python :: 3.4
